FM13_transform/__init__.py
FM13_transform/data2bufr.py
FM13_transform/resources/__init__.py
FM13_transform/resources/synop-mappings-308009.json
FM13_transform-0.0.5.dist-info/METADATA
FM13_transform-0.0.5.dist-info/WHEEL
FM13_transform-0.0.5.dist-info/top_level.txt
FM13_transform-0.0.5.dist-info/RECORD
