Metadata-Version: 2.1
Name: FM13_transform
Version: 0.0.5
Summary: Package for converting FM13 SYNOP to BUFR4 and GeoJSON
Author-email: Zhan Zhang <zhan.j.zhang@noaa.gov>, Alex Thompson <alexander.thompson@noaa.gov>
Project-URL: Homepage, https://github.com/pypa/sampleproject
Project-URL: Bug Tracker, https://github.com/pypa/sampleproject/issues
Keywords: WMO,SYNOP SHIP,FM-13,BUFR,decoding,weather,observations
Classifier: Development Status :: 1 - Planning
Requires-Python: >=3.7
Requires-Dist: csv2bufr
Requires-Dist: eccodes
Requires-Dist: pymetdecoder
Requires-Dist: cfunits
